mousebender/__init__.py
mousebender/py.typed
mousebender/simple.py
mousebender-2025.1.dist-info/licenses/LICENSE
mousebender-2025.1.dist-info/WHEEL
mousebender-2025.1.dist-info/METADATA
mousebender-2025.1.dist-info/RECORD
