Metadata-Version: 2.4
Name: mousebender
Version: 2025.1
Summary: A package for implementing various Python packaging standards.
Keywords: packaging,Simple Repository API,PEP 503,PEP 592,PEP 658,PEP 691,PEP 700,PEP 714,PEP 740,PEP 792
Author-email: Brett Cannon <brett@python.org>, Derek Keeler <derek@suchcool.ca>
Requires-Python: >=3.8
Classifier: Topic :: Software Development :: Libraries :: Python Modules
Classifier: License :: OSI Approved :: BSD License
License-File: LICENSE
Requires-Dist: packaging >= 20.9
Requires-Dist: typing-extensions>=4.6.0
Requires-Dist: sphinx ; extra == "doc"
Requires-Dist: tomli ; extra == "doc" and ( python_version < '3.11')
Requires-Dist: furo ; extra == "doc"
Requires-Dist: sphinx-copybutton ; extra == "doc"
Requires-Dist: sphinx-prompt ; extra == "doc"
Requires-Dist: pytest >= 6.0.1 ; extra == "test"
Requires-Dist: importlib-resources >= 1.4.0 ; extra == "test"
Requires-Dist: coverage[toml] >= 5.0.4 ; extra == "test"
Requires-Dist: pytest-cov >= 2.8.1 ; extra == "test"
Project-URL: Changelog, https://github.com/brettcannon/mousebender/releases
Project-URL: Documentation, https://mousebender.readthedocs.io/
Project-URL: Fiscal support, https://github.com/sponsors/brettcannon/
Project-URL: Issues, https://github.com/brettcannon/mousebender/issues
Project-URL: Repository, https://github.com/brettcannon/mousebender
Provides-Extra: doc
Provides-Extra: test
